{
  "users": [
    {
      "id": "c444",
      "name": "a",
      "email": "a@gmail.com",
      "phone": "1234567890",
      "city": "pune",
      "password": "12345"
    }
  ],
  "fooditems": [
    {
      "id": "1",
      "name": "Delicious Pizza",
      "price": 15,
      "image": "./images/f1.png",
      "category": "Pizza",
      "stock": 5,
      "qty": 1
    },
    {
      "id": "2",
      "name": "Delicious Burger",
      "price": 23,
      "image": "./images/f2.png",
      "category": "Burger",
      "stock": 10,
      "qty": 1
    },
    {
      "id": "3",
      "name": "Delicious Pizza",
      "price": 20,
      "image": "./images/f3.png",
      "category": "Pizza",
      "stock": 3,
      "qty": 1
    },
    {
      "id": "4",
      "name": "Delicious Pasta",
      "price": 18,
      "image": "./images/f4.png",
      "category": "Pasta",
      "stock": 5,
      "qty": 1
    },
    {
      "id": "5",
      "name": "Delicious French fries",
      "price": 10,
      "image": "./images/f5.png",
      "category": "Fries",
      "stock": 15,
      "qty": 1
    },
    {
      "id": "6",
      "name": "Delicious Pizza",
      "price": 10,
      "image": "./images/f6.png",
      "category": "Pizza",
      "stock": 12,
      "qty": 1
    },
    {
      "id": "7",
      "name": "Testy burger",
      "price": 12,
      "image": "./images/f7.png",
      "category": "Burger",
      "stock": 5,
      "qty": 1
    },
    {
      "id": "8",
      "name": "Testy burger",
      "price": 14,
      "image": "./images/f8.png",
      "category": "Burger",
      "stock": 5,
      "qty": 1
    },
    {
      "id": "9",
      "name": "Delicious Pasta",
      "price": 10,
      "image": "./images/f9.png",
      "category": "Pasta",
      "stock": 8,
      "qty": 1
    }
  ],
  "cart": [
    {
      "id": "1",
      "name": "Delicious Pizza",
      "price": 15,
      "image": "./images/f1.png",
      "category": "Pizza",
      "stock": 5,
      "qty": 1
    },
    {
      "id": "2",
      "name": "Delicious Burger",
      "price": 23,
      "image": "./images/f2.png",
      "category": "Burger",
      "stock": 10,
      "qty": 1
    },
    {
      "id": "3",
      "name": "Delicious Pizza",
      "price": 20,
      "image": "./images/f3.png",
      "category": "Pizza",
      "stock": 3,
      "qty": 1
    }
  ]
}